gym_unity/__init__.py
gym_unity/envs/__init__.py
gym_unity-0.28.0.dist-info/METADATA
gym_unity-0.28.0.dist-info/WHEEL
gym_unity-0.28.0.dist-info/top_level.txt
gym_unity-0.28.0.dist-info/RECORD
