Metadata-Version: 2.1
Name: gym-unity
Version: 0.28.0
Summary: Unity Machine Learning Agents Gym Interface
Home-page: https://github.com/Unity-Technologies/ml-agents
Author: Unity Technologies
Author-email: ML-Agents@unity3d.com
License: Apache License 2.0
Platform: UNKNOWN
Requires-Dist: gym (==0.20.0)
Requires-Dist: mlagents-envs (==0.28.0)
